synccanary/__init__.py
synccanary/cli.py
synccanary/synccanary.py
synccanary-0.0.1.dist-info/METADATA
synccanary-0.0.1.dist-info/WHEEL
synccanary-0.0.1.dist-info/entry_points.txt
synccanary-0.0.1.dist-info/top_level.txt
synccanary-0.0.1.dist-info/RECORD
